easyword2num/__init__.py
easyword2num/__init__.pyi
easyword2num/py.typed
easyword2num/word2num.py
easyword2num/word2num.pyi
easyword2num-0.1.3.dist-info/LICENSE
easyword2num-0.1.3.dist-info/METADATA
easyword2num-0.1.3.dist-info/WHEEL
easyword2num-0.1.3.dist-info/RECORD
