Metadata-Version: 2.1
Name: easyword2num
Version: 0.1.3
Summary: Convert numbers expressed in English to its numeric value.
License: MIT
Author: J.I. Cruz
Author-email: ji@jicruz.com
Requires-Python: >=3.8,<4.0
Classifier: License :: OSI Approved :: MIT License
Classifier: Programming Language :: Python :: 3
Classifier: Programming Language :: Python :: 3.8
Classifier: Programming Language :: Python :: 3.9
Classifier: Programming Language :: Python :: 3.10
Classifier: Programming Language :: Python :: 3.11
Classifier: Programming Language :: Python :: 3.12
